micro-benchmark/__init__.py
micro-benchmark/args_test.py
micro-benchmark/assignments_test.py
micro-benchmark/base.py
micro-benchmark/builtins_test.py
micro-benchmark/classes_test.py
micro-benchmark/create_pytests.py
micro-benchmark/decorators_test.py
micro-benchmark/dicts_test.py
micro-benchmark/direct_calls_test.py
micro-benchmark/dynamic_test.py
micro-benchmark/exceptions_test.py
micro-benchmark/external_test.py
micro-benchmark/functions_test.py
micro-benchmark/generators_test.py
micro-benchmark/imports_test.py
micro-benchmark/kwargs_test.py
micro-benchmark/lambdas_test.py
micro-benchmark/lists_test.py
micro-benchmark/mro_test.py
micro-benchmark/returns_test.py
micro-benchmark-key-errs/__init__.py
micro-benchmark-key-errs/assignments_test.py
micro-benchmark-key-errs/base.py
micro-benchmark-key-errs/classes_test.py
micro-benchmark-key-errs/create_pytests.py
micro-benchmark-key-errs/dicts_test.py
micro-benchmark-key-errs/kwargs_test.py
micro-benchmark-key-errs/lists_test.py
micro-benchmark-key-errs/parameters_test.py
pycg/__init__.py
pycg/__main__.py
pycg/pycg.py
pycg/formats/__init__.py
pycg/formats/as_graph.py
pycg/formats/base.py
pycg/formats/fasten.py
pycg/formats/simple.py
pycg/machinery/__init__.py
pycg/machinery/callgraph.py
pycg/machinery/classes.py
pycg/machinery/definitions.py
pycg/machinery/imports.py
pycg/machinery/key_err.py
pycg/machinery/modules.py
pycg/machinery/pointers.py
pycg/machinery/scopes.py
pycg/processing/__init__.py
pycg/processing/base.py
pycg/processing/cgprocessor.py
pycg/processing/keyerrprocessor.py
pycg/processing/postprocessor.py
pycg/processing/preprocessor.py
pycg/utils/__init__.py
pycg/utils/common.py
pycg/utils/constants.py
pycg-0.0.4.dist-info/LICENCE
pycg-0.0.4.dist-info/METADATA
pycg-0.0.4.dist-info/WHEEL
pycg-0.0.4.dist-info/entry_points.txt
pycg-0.0.4.dist-info/top_level.txt
pycg-0.0.4.dist-info/RECORD
