Metadata-Version: 2.1
Name: pycg
Version: 0.0.4
Summary: Practical Python Call Graphs
Home-page: https://github.com/vitsalis/pycg
Author: Vitalis Salis
Author-email: vitsalis@gmail.com
License: Apache Software License
Platform: UNKNOWN
Classifier: License :: OSI Approved :: Apache Software License
Classifier: Programming Language :: Python :: 3
